setup.cfg
setup.py
speedyio/__init__.py
speedyio/errors.py
speedyio.egg-info/PKG-INFO
speedyio.egg-info/SOURCES.txt
speedyio.egg-info/dependency_links.txt
speedyio.egg-info/requires.txt
speedyio.egg-info/top_level.txt
speedyio/basic/__init__.py
speedyio/basic/askfor.py
speedyio/basic/bold_print.py
speedyio/basic/chooseone.py
speedyio/basic/error.py
speedyio/basic/info.py
speedyio/basic/plain_print.py
speedyio/basic/success.py
speedyio/basic/yesno.py
speedyio/entities/__init__.py
speedyio/entities/item.py
speedyio/interactive/__init__.py
speedyio/interactive/askfor.py
speedyio/interactive/bold_print.py
speedyio/interactive/chooseone.py
speedyio/interactive/error.py
speedyio/interactive/info.py
speedyio/interactive/plain_print.py
speedyio/interactive/success.py
speedyio/interactive/yesno.py