Metadata-Version: 1.1
Name: speedyio
Version: 0.4
Summary: Input from console made easy and interactive for Python
Home-page: https://github.com/arpitbbhayani/speedyio
Author: Arpit Bhayani
Author-email: arpit.b.bhayani@gmail.com
License: UNKNOWN
Download-URL: https://github.com/arpitbbhayani/speedyio
Keywords: io,cli
Platform: UNKNOWN
